{
    "MPN": [
        false,
        "CC0402M_X7R8BB333"
    ],
    "base": "6c8302f6-8c7d-4cb2-b04f-e3ce9fa8b311",
    "datasheet": [
        false,
        "http://www.yageo.com/portal/product/productDocs.jsp?YageoPartNumber=CC0402MRX7R8BB333"
    ],
    "description": [
        false,
        "Ceramic Capacitor 33 nF 25 V X7R"
    ],
    "inherit_model": true,
    "inherit_tags": true,
    "manufacturer": [
        true,
        ""
    ],
    "model": "96c366ee-a963-41a0-9cc8-54c646979695",
    "orderable_MPNs": {
        "2934a5d3-3a4c-40eb-b991-b681afd84cce": "CC0402MRX7R8BB333"
    },
    "parametric": {
        "table": "capacitors",
        "tolerance": "20",
        "type": "X7R",
        "value": "3.3000e-08",
        "wvdc": "25.0"
    },
    "tags": [],
    "type": "part",
    "uuid": "dbd9a6af-1d4c-4f18-ac04-d6bf75fb71eb",
    "value": [
        false,
        "33 nF"
    ]
}