{
    "MPN": [
        false,
        "CC0402J_X7R9BB271"
    ],
    "base": "6c8302f6-8c7d-4cb2-b04f-e3ce9fa8b311",
    "datasheet": [
        false,
        "http://www.yageo.com/portal/product/productDocs.jsp?YageoPartNumber=CC0402JRX7R9BB271"
    ],
    "description": [
        false,
        "Ceramic Capacitor 270 pF 50 V X7R"
    ],
    "inherit_model": true,
    "inherit_tags": true,
    "manufacturer": [
        true,
        ""
    ],
    "model": "96c366ee-a963-41a0-9cc8-54c646979695",
    "orderable_MPNs": {
        "b5d7da7c-b067-43c5-afe0-e54a1d8db307": "CC0402JRX7R9BB271"
    },
    "parametric": {
        "table": "capacitors",
        "tolerance": "5",
        "type": "X7R",
        "value": "2.7000e-10",
        "wvdc": "50.0"
    },
    "tags": [],
    "type": "part",
    "uuid": "8f27fb95-f8e9-4a85-9911-f0690e345af6",
    "value": [
        false,
        "270 pF"
    ]
}