{
    "MPN": [
        false,
        "RMCF0805F_51R0"
    ],
    "base": "44c3cea3-61ef-4e64-98c4-280de2e86c33",
    "datasheet": [
        true,
        ""
    ],
    "description": [
        false,
        "SMD Resistor 0805, 51 ohm, 1%, 0.125W (RMCF)"
    ],
    "inherit_model": true,
    "inherit_tags": true,
    "manufacturer": [
        true,
        ""
    ],
    "model": "96c366ee-a963-41a0-9cc8-54c646979695",
    "orderable_MPNs": {
        "23d20d67-4fe7-4704-b926-1ee213a8146e": "RMCF0805FB51R0",
        "27e7aced-b8c8-46be-97b7-e184ee705f53": "RMCF0805FG51R0",
        "46d90019-4a79-4a92-8856-6c97fa2b777c": "RMCF0805FT51R0"
    },
    "parametric": {
        "pmax": "0.125",
        "table": "resistors",
        "tolerance": "1.0",
        "value": "51.0"
    },
    "tags": [],
    "type": "part",
    "uuid": "87447ec1-b1ec-43d7-a1ec-2ea0b124abd2",
    "value": [
        false,
        "51 \u2126"
    ]
}