{
    "MPN": [
        false,
        "RMCF0805J_11M0"
    ],
    "base": "44c3cea3-61ef-4e64-98c4-280de2e86c33",
    "datasheet": [
        true,
        ""
    ],
    "description": [
        false,
        "SMD Resistor 0805, 11 Mohm, 5%, 0.125W (RMCF)"
    ],
    "inherit_model": true,
    "inherit_tags": true,
    "manufacturer": [
        true,
        ""
    ],
    "model": "96c366ee-a963-41a0-9cc8-54c646979695",
    "orderable_MPNs": {
        "04231ebd-b8e0-4b92-b7bc-136d37102f83": "RMCF0805JG11M0",
        "69be18e0-25da-4825-a5ae-e5eb763ec01f": "RMCF0805JB11M0",
        "a63d0b8a-b7d1-4fd2-81ec-108bdaba8f1b": "RMCF0805JT11M0"
    },
    "parametric": {
        "pmax": "0.125",
        "table": "resistors",
        "tolerance": "5.0",
        "value": "11000000.0"
    },
    "tags": [],
    "type": "part",
    "uuid": "34c69853-bd8d-489f-9e4d-78b9d20a82c9",
    "value": [
        false,
        "11 M\u2126"
    ]
}