{
    "MPN": [
        false,
        "RMCF0805F_3K60"
    ],
    "base": "44c3cea3-61ef-4e64-98c4-280de2e86c33",
    "datasheet": [
        true,
        ""
    ],
    "description": [
        false,
        "SMD Resistor 0805, 3.6 Kohm, 1%, 0.125W (RMCF)"
    ],
    "inherit_model": true,
    "inherit_tags": true,
    "manufacturer": [
        true,
        ""
    ],
    "model": "96c366ee-a963-41a0-9cc8-54c646979695",
    "orderable_MPNs": {
        "5656b3ec-7ae5-49e7-80d7-03bf56ad12c0": "RMCF0805FT3K60",
        "7863fdd8-5624-4674-92f5-e47369841a3a": "RMCF0805FG3K60",
        "d2332e1c-3a11-4a1f-8adb-02b2402ce522": "RMCF0805FB3K60"
    },
    "parametric": {
        "pmax": "0.125",
        "table": "resistors",
        "tolerance": "1.0",
        "value": "3600.0"
    },
    "tags": [],
    "type": "part",
    "uuid": "5ce77a67-5fc1-4083-8812-a89c9ea6acd3",
    "value": [
        false,
        "3.6 k\u2126"
    ]
}