{
    "MPN": [
        false,
        "RMCF0805F_91R0"
    ],
    "base": "44c3cea3-61ef-4e64-98c4-280de2e86c33",
    "datasheet": [
        true,
        ""
    ],
    "description": [
        false,
        "SMD Resistor 0805, 91 ohm, 1%, 0.125W (RMCF)"
    ],
    "inherit_model": true,
    "inherit_tags": true,
    "manufacturer": [
        true,
        ""
    ],
    "model": "96c366ee-a963-41a0-9cc8-54c646979695",
    "orderable_MPNs": {
        "51a6d2ea-4934-4c7a-a204-4c13ca70a303": "RMCF0805FT91R0",
        "673e4e47-b233-46c6-b489-43402ff33d0d": "RMCF0805FB91R0",
        "f41e883e-1a84-402b-8565-3d0110f4cb8d": "RMCF0805FG91R0"
    },
    "parametric": {
        "pmax": "0.125",
        "table": "resistors",
        "tolerance": "1.0",
        "value": "91.0"
    },
    "tags": [],
    "type": "part",
    "uuid": "d77a5e5a-553a-4d87-ab84-b1bc46f9010a",
    "value": [
        false,
        "91 \u2126"
    ]
}