{
    "MPN": [
        false,
        "RMCF1206F_27R4"
    ],
    "base": "a1c9107f-9ac7-4662-b309-616e4b4d3e6e",
    "datasheet": [
        true,
        ""
    ],
    "description": [
        false,
        "SMD Resistor 1206, 27.4 ohm, 1%, 0.25W (RMCF)"
    ],
    "inherit_model": true,
    "inherit_tags": true,
    "manufacturer": [
        true,
        ""
    ],
    "model": "96c366ee-a963-41a0-9cc8-54c646979695",
    "orderable_MPNs": {
        "515dff68-629c-4697-b83a-2526410c2d46": "RMCF1206FT27R4",
        "8c3d44fb-b3ce-4a9a-9a32-3c04b5138b41": "RMCF1206FB27R4",
        "e9ceb444-4ad9-427a-bde5-b1d21c121ebd": "RMCF1206FG27R4"
    },
    "parametric": {
        "pmax": "0.25",
        "table": "resistors",
        "tolerance": "1.0",
        "value": "27.4"
    },
    "tags": [],
    "type": "part",
    "uuid": "8f8611b7-2bfa-4f5b-b724-a07724842cb9",
    "value": [
        false,
        "27.4 \u2126"
    ]
}