{
    "MPN": [
        false,
        "RMCF1206F_6K98"
    ],
    "base": "a1c9107f-9ac7-4662-b309-616e4b4d3e6e",
    "datasheet": [
        true,
        ""
    ],
    "description": [
        false,
        "SMD Resistor 1206, 6.98 Kohm, 1%, 0.25W (RMCF)"
    ],
    "inherit_model": true,
    "inherit_tags": true,
    "manufacturer": [
        true,
        ""
    ],
    "model": "96c366ee-a963-41a0-9cc8-54c646979695",
    "orderable_MPNs": {
        "03642dd6-437b-44c7-a634-f03600702919": "RMCF1206FT6K98",
        "1f27a373-8e94-4c9c-93fe-be6656fc0969": "RMCF1206FG6K98",
        "f317341a-e661-4425-818b-5a0fa822deec": "RMCF1206FB6K98"
    },
    "parametric": {
        "pmax": "0.25",
        "table": "resistors",
        "tolerance": "1.0",
        "value": "6980.0"
    },
    "tags": [],
    "type": "part",
    "uuid": "7fc5ef4c-4eab-4e83-a8ed-dc22721b05eb",
    "value": [
        false,
        "6.98 k\u2126"
    ]
}