{
    "MPN": [
        false,
        "RMCF1206F_1M58"
    ],
    "base": "a1c9107f-9ac7-4662-b309-616e4b4d3e6e",
    "datasheet": [
        true,
        ""
    ],
    "description": [
        false,
        "SMD Resistor 1206, 1.58 Mohm, 1%, 0.25W (RMCF)"
    ],
    "inherit_model": true,
    "inherit_tags": true,
    "manufacturer": [
        true,
        ""
    ],
    "model": "96c366ee-a963-41a0-9cc8-54c646979695",
    "orderable_MPNs": {
        "19816276-3739-438c-b790-f5399bc54e1b": "RMCF1206FT1M58",
        "329b16a4-e6f8-4473-98c2-de49cf666321": "RMCF1206FG1M58",
        "40f0347f-f2fe-4fca-89f6-5a29a322c267": "RMCF1206FB1M58"
    },
    "parametric": {
        "pmax": "0.25",
        "table": "resistors",
        "tolerance": "1.0",
        "value": "1580000.0"
    },
    "tags": [],
    "type": "part",
    "uuid": "e5f0fd42-3050-468d-a58d-970c717c65be",
    "value": [
        false,
        "1.58 M\u2126"
    ]
}