{
    "MPN": [
        false,
        "RMCF1206F_143K"
    ],
    "base": "a1c9107f-9ac7-4662-b309-616e4b4d3e6e",
    "datasheet": [
        true,
        ""
    ],
    "description": [
        false,
        "SMD Resistor 1206, 143 Kohm, 1%, 0.25W (RMCF)"
    ],
    "inherit_model": true,
    "inherit_tags": true,
    "manufacturer": [
        true,
        ""
    ],
    "model": "96c366ee-a963-41a0-9cc8-54c646979695",
    "orderable_MPNs": {
        "42876361-f2c2-4bdd-a8f1-7257f4e4081c": "RMCF1206FG143K",
        "4d78423c-29d9-4c9b-bf70-2f1cf4768b40": "RMCF1206FT143K",
        "f52b5b6e-0b78-4a93-8698-d1841dccccdf": "RMCF1206FB143K"
    },
    "parametric": {
        "pmax": "0.25",
        "table": "resistors",
        "tolerance": "1.0",
        "value": "143000.0"
    },
    "tags": [],
    "type": "part",
    "uuid": "95ea3fd8-bbe7-48a4-8df9-c8036027e580",
    "value": [
        false,
        "143 k\u2126"
    ]
}