{
    "MPN": [
        false,
        "RC1608F623CS"
    ],
    "base": "7d6fb163-8671-4026-91b0-5137e70ff04b",
    "datasheet": [
        true,
        ""
    ],
    "description": [
        false,
        "Chip Resistor 62 k\u2126 1% 0.1W"
    ],
    "inherit_model": true,
    "inherit_tags": true,
    "manufacturer": [
        true,
        ""
    ],
    "model": "96c366ee-a963-41a0-9cc8-54c646979695",
    "parametric": {
        "pmax": "0.1",
        "table": "resistors",
        "tolerance": "1",
        "value": "62000.0"
    },
    "tags": [],
    "type": "part",
    "uuid": "7c63758e-dd03-466d-a301-c6dda595ec0f",
    "value": [
        false,
        "62 k\u2126"
    ]
}