{
    "MPN": [
        false,
        "CC1210K_X5R8BB226"
    ],
    "base": "a9067048-3070-4df6-b961-c0d409b7f4d0",
    "datasheet": [
        false,
        "http://www.yageo.com/portal/product/productDocs.jsp?YageoPartNumber=CC1210KKX5R8BB226"
    ],
    "description": [
        false,
        "Ceramic Capacitor 22 \u00b5F 25 V X5R"
    ],
    "inherit_model": true,
    "inherit_tags": true,
    "manufacturer": [
        true,
        ""
    ],
    "model": "96c366ee-a963-41a0-9cc8-54c646979695",
    "orderable_MPNs": {
        "f1ff424d-5c59-4f05-b5a1-93c54b1fd5fd": "CC1210KKX5R8BB226"
    },
    "parametric": {
        "table": "capacitors",
        "tolerance": "10",
        "type": "X5R",
        "value": "2.2000e-05",
        "wvdc": "25.0"
    },
    "tags": [],
    "type": "part",
    "uuid": "f3ca6c30-0470-4c8d-a3b3-4c9c3e96dc33",
    "value": [
        false,
        "22 \u00b5F"
    ]
}