{
    "MPN": [
        false,
        "RT0805DRE073K"
    ],
    "base": "4b53ea1f-13f0-4d5e-b537-dd47535216de",
    "datasheet": [
        true,
        ""
    ],
    "description": [
        false,
        "SMD Resistor High Precison High Stability Chip Resistor (RT) 3.09 k\u03a9 0.5% 0.125W 50ppm/C"
    ],
    "inherit_tags": true,
    "manufacturer": [
        true,
        ""
    ],
    "parametric": {
        "pmax": "0.125",
        "table": "resistors",
        "tolerance": "0.5",
        "value": "3090.0"
    },
    "tags": [],
    "type": "part",
    "uuid": "d81dc25f-af3a-4ecd-a55f-ea1347562c47",
    "value": [
        false,
        "3.09 k\u03a9"
    ]
}