{
    "MPN": [
        false,
        "ERJ-8ENF13R0"
    ],
    "base": "3cfc0897-cdc4-462f-ade4-f41bdf2bac54",
    "datasheet": [
        false,
        "https://industrial.panasonic.com/cdbs/www-data/pdf/RDA0000/AOA0000C304.pdf"
    ],
    "description": [
        false,
        "Chip Resistor 13 \u2126 1% 0.25W"
    ],
    "inherit_model": true,
    "inherit_tags": true,
    "manufacturer": [
        true,
        ""
    ],
    "model": "96c366ee-a963-41a0-9cc8-54c646979695",
    "orderable_MPNs": {
        "27f730d5-9e2c-4b3f-8458-068688b814c8": "ERJ-8ENF13R0V"
    },
    "parametric": {
        "pmax": "0.25",
        "table": "resistors",
        "tolerance": "1.0",
        "value": "13.0"
    },
    "tags": [],
    "type": "part",
    "uuid": "8526fada-cdaf-4c92-8472-80522562d605",
    "value": [
        false,
        "13 \u2126"
    ]
}