{
    "MPN": [
        false,
        "RC2012F391CS"
    ],
    "base": "4783cd85-1010-4602-8fe2-459f0e0c26e9",
    "datasheet": [
        true,
        ""
    ],
    "description": [
        false,
        "Chip Resistor 390 \u2126 1% 0.125W"
    ],
    "inherit_model": true,
    "inherit_tags": true,
    "manufacturer": [
        true,
        ""
    ],
    "model": "96c366ee-a963-41a0-9cc8-54c646979695",
    "parametric": {
        "pmax": "0.125",
        "table": "resistors",
        "tolerance": "1",
        "value": "390.0"
    },
    "tags": [],
    "type": "part",
    "uuid": "31da69be-fe92-4191-926b-1edad772f520",
    "value": [
        false,
        "390 \u2126"
    ]
}