{
    "MPN": [
        false,
        "GRM158C80G226ME01"
    ],
    "base": "dab5ee1d-b645-4349-ae88-f948c7a721b1",
    "datasheet": [
        true,
        ""
    ],
    "description": [
        false,
        "Ceramic Capacitor 22 \u00b5F 4 VDC X6S"
    ],
    "inherit_model": true,
    "inherit_tags": true,
    "manufacturer": [
        true,
        ""
    ],
    "orderable_MPNs": {
        "70daee9a-1771-4943-bbe3-8bca6a0ab857": "GRM158C80G226ME01D",
        "9430989b-6653-493d-ab89-6a9449df3260": "GRM158C80G226ME01J"
    },
    "parametric": {
        "table": "capacitors",
        "type": "X6S",
        "value": "2.2000e-05",
        "wvdc": "4.0"
    },
    "tags": [],
    "type": "part",
    "uuid": "ae1bd62c-ba8f-493d-aefe-415cf90c63bc",
    "value": [
        false,
        "22 \u00b5F"
    ]
}