{
    "MPN": [
        false,
        "ERJ-2RKD5103"
    ],
    "base": "7f3cde91-d80e-4fd9-9053-b6cbe78f31fd",
    "datasheet": [
        false,
        "https://industrial.panasonic.com/cdbs/www-data/pdf/RDA0000/AOA0000C304.pdf"
    ],
    "description": [
        false,
        "Chip Resistor 510 k\u2126 0% 0.063W"
    ],
    "inherit_model": true,
    "inherit_tags": true,
    "manufacturer": [
        true,
        ""
    ],
    "model": "96c366ee-a963-41a0-9cc8-54c646979695",
    "orderable_MPNs": {
        "bee328a9-6121-4e23-b99c-6cd84f45d7f8": "ERJ-2RKD5103X"
    },
    "parametric": {
        "pmax": "0.063",
        "table": "resistors",
        "tolerance": "0.5",
        "value": "510000.0"
    },
    "tags": [],
    "type": "part",
    "uuid": "631359e5-5b0b-42a8-9245-b027e4a0f96f",
    "value": [
        false,
        "510 k\u2126"
    ]
}