{
    "manufacturer": "MaxLinear",
    "name": "XR21V1410IL16-F",
    "pins": {
        "025143d9-8901-4a43-9637-88d2d986cb62": {
            "direction": "power_input",
            "names": [],
            "primary_name": "VCC",
            "swap_group": 0
        },
        "044dc7b5-7822-4c1f-88d9-801b8b9c2542": {
            "direction": "bidirectional",
            "names": [
                "CD#"
            ],
            "primary_name": "GPIO1",
            "swap_group": 0
        },
        "1075a9af-1ec3-4125-8c12-3088a43abadc": {
            "direction": "bidirectional",
            "names": [
                "DTR#"
            ],
            "primary_name": "GPIO3",
            "swap_group": 0
        },
        "2b3f696d-f768-49ea-ae71-e54842b952e7": {
            "direction": "power_input",
            "names": [],
            "primary_name": "GND",
            "swap_group": 0
        },
        "363972ff-0363-4965-be29-b36ddba36065": {
            "direction": "output",
            "names": [],
            "primary_name": "TX",
            "swap_group": 0
        },
        "53aa3b94-6e28-4170-8d74-c74fb01f8c91": {
            "direction": "bidirectional",
            "names": [
                "RI#",
                "RWK#"
            ],
            "primary_name": "GPIO0",
            "swap_group": 0
        },
        "647f8c11-b8c4-4410-ba2e-0de112dab06e": {
            "direction": "bidirectional",
            "names": [],
            "primary_name": "SDA",
            "swap_group": 0
        },
        "76bb9f7b-e504-47ef-b0ff-d5636d44a89b": {
            "direction": "bidirectional",
            "names": [
                "DSR#"
            ],
            "primary_name": "GPIO2",
            "swap_group": 0
        },
        "81939c1f-5709-4b80-9255-4a550f146385": {
            "direction": "input",
            "names": [],
            "primary_name": "RX",
            "swap_group": 0
        },
        "8f293709-b7cd-4ee0-8eb2-508eb81c79de": {
            "direction": "bidirectional",
            "names": [],
            "primary_name": "USBD+",
            "swap_group": 0
        },
        "97e185d7-7b62-4ca6-80d8-7d7ac5afc7ff": {
            "direction": "bidirectional",
            "names": [
                "RTS#",
                "RS485"
            ],
            "primary_name": "GPIO5",
            "swap_group": 0
        },
        "cdc55b0d-ff0c-45da-8410-76827f3cb311": {
            "direction": "output",
            "names": [],
            "primary_name": "LOWPOWER",
            "swap_group": 0
        },
        "d27bb9b7-2015-42dc-bbd1-a8c0c2f49630": {
            "direction": "bidirectional",
            "names": [],
            "primary_name": "SCL",
            "swap_group": 0
        },
        "e0d88d95-4e26-46f8-a967-e015000e8f1b": {
            "direction": "bidirectional",
            "names": [
                "CTS#"
            ],
            "primary_name": "GPIO4",
            "swap_group": 0
        },
        "e847eef7-01f5-457b-a585-0b196ecb2591": {
            "direction": "bidirectional",
            "names": [],
            "primary_name": "USBD-",
            "swap_group": 0
        }
    },
    "type": "unit",
    "uuid": "095d8a66-d296-496d-b808-5467af22012c"
}