{
    "MPN": [
        false,
        "RMCF0402F_15R4"
    ],
    "base": "ea604828-27df-4283-ba01-a6e6eea31f62",
    "datasheet": [
        true,
        ""
    ],
    "description": [
        false,
        "SMD Resistor 0402, 15.4 ohm, 1%, 0.0625W (RMCF)"
    ],
    "inherit_model": true,
    "inherit_tags": true,
    "manufacturer": [
        true,
        ""
    ],
    "model": "96c366ee-a963-41a0-9cc8-54c646979695",
    "orderable_MPNs": {
        "66fc5c48-a7e6-47eb-b578-6e3a34d11163": "RMCF0402FB15R4",
        "90434d71-d6cb-4766-8f13-8851de46e033": "RMCF0402FG15R4",
        "fd9dcf7a-ec35-429e-9c4c-fb2a21dd60fa": "RMCF0402FT15R4"
    },
    "parametric": {
        "pmax": "0.063",
        "table": "resistors",
        "tolerance": "1.0",
        "value": "15.4"
    },
    "tags": [],
    "type": "part",
    "uuid": "2d8bdc00-0375-4601-b29b-e23805787381",
    "value": [
        false,
        "15.4 \u2126"
    ]
}