{
    "MPN": [
        false,
        "RMCF0402F_8M20"
    ],
    "base": "ea604828-27df-4283-ba01-a6e6eea31f62",
    "datasheet": [
        true,
        ""
    ],
    "description": [
        false,
        "SMD Resistor 0402, 8.2 Mohm, 1%, 0.0625W (RMCF)"
    ],
    "inherit_model": true,
    "inherit_tags": true,
    "manufacturer": [
        true,
        ""
    ],
    "model": "96c366ee-a963-41a0-9cc8-54c646979695",
    "orderable_MPNs": {
        "1cd6d90f-6a66-4c81-9dda-cfaf9d825418": "RMCF0402FT8M20",
        "43cee9d5-99b9-4cb4-a9e7-54c4b68dfd07": "RMCF0402FB8M20",
        "f34f4e66-c0e5-4df3-a3a3-e30d123d915a": "RMCF0402FG8M20"
    },
    "parametric": {
        "pmax": "0.063",
        "table": "resistors",
        "tolerance": "1.0",
        "value": "8199999.999999999"
    },
    "tags": [],
    "type": "part",
    "uuid": "c9e7893c-8bba-4bee-8cda-c93f717f2d5a",
    "value": [
        false,
        "8.2 M\u2126"
    ]
}