{
    "MPN": [
        false,
        "RMCF0402J_1R60"
    ],
    "base": "ea604828-27df-4283-ba01-a6e6eea31f62",
    "datasheet": [
        true,
        ""
    ],
    "description": [
        false,
        "SMD Resistor 0402, 1.6 ohm, 5%, 0.0625W (RMCF)"
    ],
    "inherit_model": true,
    "inherit_tags": true,
    "manufacturer": [
        true,
        ""
    ],
    "model": "96c366ee-a963-41a0-9cc8-54c646979695",
    "orderable_MPNs": {
        "1c44e0f0-cb31-469a-8d20-4d9dca9208e3": "RMCF0402JT1R60",
        "313d2f72-d4e1-4563-ba08-ee1396d0f651": "RMCF0402JB1R60",
        "a07501ea-0773-4aba-a84b-542f4c3ba1eb": "RMCF0402JG1R60"
    },
    "parametric": {
        "pmax": "0.063",
        "table": "resistors",
        "tolerance": "5.0",
        "value": "1.6"
    },
    "tags": [],
    "type": "part",
    "uuid": "4f82edf9-0078-4efe-b0f1-1fce9069039e",
    "value": [
        false,
        "1.6 \u2126"
    ]
}