{
    "MPN": [
        false,
        "RMCF0402F_2R21"
    ],
    "base": "ea604828-27df-4283-ba01-a6e6eea31f62",
    "datasheet": [
        true,
        ""
    ],
    "description": [
        false,
        "SMD Resistor 0402, 2.21 ohm, 1%, 0.0625W (RMCF)"
    ],
    "inherit_model": true,
    "inherit_tags": true,
    "manufacturer": [
        true,
        ""
    ],
    "model": "96c366ee-a963-41a0-9cc8-54c646979695",
    "orderable_MPNs": {
        "0ab2aaef-ba26-4972-b35a-8e434ee42479": "RMCF0402FG2R21",
        "410b002f-4a14-4f05-900e-e8e97e05fb72": "RMCF0402FB2R21",
        "a7fba088-0caf-4b0d-bf90-6d167195d4fc": "RMCF0402FT2R21"
    },
    "parametric": {
        "pmax": "0.063",
        "table": "resistors",
        "tolerance": "1.0",
        "value": "2.21"
    },
    "tags": [],
    "type": "part",
    "uuid": "494c09f9-da13-4e20-90fb-20bec37d870f",
    "value": [
        false,
        "2.21 \u2126"
    ]
}