{
    "MPN": [
        false,
        "EEUFC1A152"
    ],
    "base": "fcad7f25-ca86-5e41-959c-ecc2f7085d93",
    "datasheet": [
        true,
        "https://industrial.panasonic.com/cdbs/www-data/pdf/RDF0000/ABA0000C1209.pdf"
    ],
    "description": [
        false,
        "1500 \u03bcF, 10V, 20%, 3000h Aluminium Electrolytic Capacitor"
    ],
    "inherit_model": true,
    "inherit_tags": false,
    "manufacturer": [
        true,
        "Panasonic"
    ],
    "model": "28b81198-2d68-55dd-b1aa-c567fdffd887",
    "parametric": {
        "table": "capacitors",
        "type": "Electrolytic",
        "value": "1500.0e-06",
        "wvdc": "10"
    },
    "tags": [
        "passive",
        "th",
        "capacitor",
        "electrolytic",
        "polarized",
        "5mm",
        "10V"
    ],
    "type": "part",
    "uuid": "37ab3694-bf4d-50dd-ae16-90005288ca44",
    "value": [
        false,
        "1500 \u03bcF (10V)"
    ]
}