{
    "MPN": [
        false,
        "CC0603B_NPO9BNR60"
    ],
    "base": "6f27eb66-40e7-4dcc-baa1-887f336d41ed",
    "datasheet": [
        false,
        "http://www.yageo.com/portal/product/productDocs.jsp?YageoPartNumber=CC0603BRNPO9BNR60"
    ],
    "description": [
        false,
        "Ceramic Capacitor 600 fF 50 V NP0"
    ],
    "inherit_model": true,
    "inherit_tags": true,
    "manufacturer": [
        true,
        ""
    ],
    "model": "96c366ee-a963-41a0-9cc8-54c646979695",
    "orderable_MPNs": {
        "40adecee-4246-4eec-bc5d-221d8c3e2bef": "CC0603BRNPO9BNR60"
    },
    "parametric": {
        "table": "capacitors",
        "tolerance": "20",
        "type": "C0G/NP0",
        "value": "6.0000e-13",
        "wvdc": "50.0"
    },
    "tags": [],
    "type": "part",
    "uuid": "60b1165b-8173-4762-a78f-db853fe77fe5",
    "value": [
        false,
        "600 fF"
    ]
}