{
    "MPN": [
        false,
        "CC0603K_X7R9BB183"
    ],
    "base": "6f27eb66-40e7-4dcc-baa1-887f336d41ed",
    "datasheet": [
        false,
        "http://www.yageo.com/portal/product/productDocs.jsp?YageoPartNumber=CC0603KPX7R9BB183"
    ],
    "description": [
        false,
        "Ceramic Capacitor 18 nF 50 V X7R"
    ],
    "inherit_model": true,
    "inherit_tags": true,
    "manufacturer": [
        true,
        ""
    ],
    "model": "96c366ee-a963-41a0-9cc8-54c646979695",
    "orderable_MPNs": {
        "17c2a7f6-bcc8-4245-a0c5-25c6ff38f027": "CC0603KPX7R9BB183",
        "674bcdc6-397a-447c-ab9f-c59a98a5266c": "CC0603KRX7R9BB183"
    },
    "parametric": {
        "table": "capacitors",
        "tolerance": "10",
        "type": "X7R",
        "value": "1.8000e-08",
        "wvdc": "50.0"
    },
    "tags": [],
    "type": "part",
    "uuid": "f2f74098-d769-4880-9bcf-291069c6e1d9",
    "value": [
        false,
        "18 nF"
    ]
}