{
    "MPN": [
        false,
        "GRM31C5C2E183JWA3"
    ],
    "base": "7467d5b0-518e-419a-b0d7-0be6319862f7",
    "datasheet": [
        true,
        ""
    ],
    "description": [
        false,
        "Ceramic Capacitor 18 nF 250 VDC C0G/NP0"
    ],
    "inherit_model": true,
    "inherit_tags": true,
    "manufacturer": [
        true,
        ""
    ],
    "orderable_MPNs": {
        "19d8445d-078a-425d-9126-3420a824f7b0": "GRM31C5C2E183JWA3K",
        "83856159-75dd-4516-af83-29a4fc1cf28a": "GRM31C5C2E183JWA3L"
    },
    "parametric": {
        "table": "capacitors",
        "type": "C0G/NP0",
        "value": "1.8000e-08",
        "wvdc": "250.0"
    },
    "tags": [],
    "type": "part",
    "uuid": "b9bebf68-6fa7-456f-ab8a-54c297e6c17d",
    "value": [
        false,
        "18 nF"
    ]
}