{
    "MPN": [
        false,
        "GRM185C80E475ME15"
    ],
    "base": "cab72b27-6d92-47d2-9694-d5f2b4b74d91",
    "datasheet": [
        false,
        "https://www.murata.com/en-us/products/productdetail.aspx?partno=GRM185C80E475ME15%23"
    ],
    "description": [
        false,
        "MLCC General Purpose 4.7 \u00b5F, 2.5 V, X6S"
    ],
    "inherit_model": true,
    "inherit_tags": true,
    "manufacturer": [
        true,
        ""
    ],
    "model": "96c366ee-a963-41a0-9cc8-54c646979695",
    "orderable_MPNs": {},
    "parametric": {
        "table": "capacitors",
        "tolerance": "20",
        "type": "X6S",
        "value": "4.7000e-06",
        "wvdc": "2.5"
    },
    "tags": [],
    "type": "part",
    "uuid": "094f6ad4-d062-489c-a35b-99c08c72a7c4",
    "value": [
        false,
        "4.7 \u00b5F"
    ]
}