{
    "MPN": [
        false,
        "RC0603FR-0718K2L"
    ],
    "base": "9954497f-10af-4158-934b-3b53068f6de4",
    "datasheet": [
        true,
        ""
    ],
    "description": [
        false,
        "SMD Resistor General Purpose 18.2 k\u03a9 1% 0.1W"
    ],
    "inherit_tags": true,
    "manufacturer": [
        true,
        ""
    ],
    "parametric": {
        "pmax": "0.1",
        "table": "resistors",
        "tolerance": "1.0",
        "value": "18200.0"
    },
    "tags": [],
    "type": "part",
    "uuid": "e80397b3-c8ad-4f7c-a937-11f06a193d09",
    "value": [
        false,
        "18.2 k\u03a9"
    ]
}