{
    "MPN": [
        false,
        "RC0603DR-073K16L"
    ],
    "base": "9954497f-10af-4158-934b-3b53068f6de4",
    "datasheet": [
        true,
        ""
    ],
    "description": [
        false,
        "SMD Resistor General Purpose 3.16 k\u03a9 0.5% 0.1W"
    ],
    "inherit_tags": true,
    "manufacturer": [
        true,
        ""
    ],
    "parametric": {
        "pmax": "0.1",
        "table": "resistors",
        "tolerance": "0.5",
        "value": "3160.0"
    },
    "tags": [],
    "type": "part",
    "uuid": "44f2131f-49b5-48a9-803a-4e91ec5f7068",
    "value": [
        false,
        "3.16 k\u03a9"
    ]
}