{
    "MPN": [
        false,
        "RC0603FR-0744R2L"
    ],
    "base": "9954497f-10af-4158-934b-3b53068f6de4",
    "datasheet": [
        true,
        ""
    ],
    "description": [
        false,
        "SMD Resistor General Purpose 44.2 \u03a9 1% 0.1W"
    ],
    "inherit_tags": true,
    "manufacturer": [
        true,
        ""
    ],
    "parametric": {
        "pmax": "0.1",
        "table": "resistors",
        "tolerance": "1.0",
        "value": "44.2"
    },
    "tags": [],
    "type": "part",
    "uuid": "97b1044d-2c58-4269-a28f-2195e8d4d268",
    "value": [
        false,
        "44.2 \u03a9"
    ]
}