{
    "MPN": [
        false,
        "ERJ-6RBD3301"
    ],
    "base": "3b6ec949-50f9-4ac5-a9d6-fa2ae04a8869",
    "datasheet": [
        false,
        "https://industrial.panasonic.com/cdbs/www-data/pdf/RDA0000/AOA0000C304.pdf"
    ],
    "description": [
        false,
        "Chip Resistor 3.3 k\u2126 0% 0.1W"
    ],
    "inherit_model": true,
    "inherit_tags": true,
    "manufacturer": [
        true,
        ""
    ],
    "model": "96c366ee-a963-41a0-9cc8-54c646979695",
    "orderable_MPNs": {
        "8ed0670f-c7c8-49a9-9eec-dfaf31cbcc6e": "ERJ-6RBD3301V"
    },
    "parametric": {
        "pmax": "0.1",
        "table": "resistors",
        "tolerance": "0.5",
        "value": "3300.0"
    },
    "tags": [],
    "type": "part",
    "uuid": "fa10dd7e-db19-4be0-8ae2-ff1868ccc1fb",
    "value": [
        false,
        "3.3 k\u2126"
    ]
}