{
    "MPN": [
        false,
        "ERJ-6ENF3092"
    ],
    "base": "3b6ec949-50f9-4ac5-a9d6-fa2ae04a8869",
    "datasheet": [
        false,
        "https://industrial.panasonic.com/cdbs/www-data/pdf/RDA0000/AOA0000C304.pdf"
    ],
    "description": [
        false,
        "Chip Resistor 30.9 k\u2126 1% 0.125W"
    ],
    "inherit_model": true,
    "inherit_tags": true,
    "manufacturer": [
        true,
        ""
    ],
    "model": "96c366ee-a963-41a0-9cc8-54c646979695",
    "orderable_MPNs": {
        "85f0b2cd-9ee5-433a-9e9f-fcb942ce145c": "ERJ-6ENF3092V"
    },
    "parametric": {
        "pmax": "0.125",
        "table": "resistors",
        "tolerance": "1.0",
        "value": "30900.0"
    },
    "tags": [],
    "type": "part",
    "uuid": "683124a0-51ef-43f6-89fa-864d9ff94ad1",
    "value": [
        false,
        "30.9 k\u2126"
    ]
}