{
    "MPN": [
        false,
        "C1005NP01H040C050BA"
    ],
    "base": "58b92388-cb19-4e12-9c56-4cb3bf795304",
    "datasheet": [
        false,
        "https://product.tdk.com/info/en/documents/chara_sheet/C1005NP01H040C050BA.pdf"
    ],
    "description": [
        false,
        "Ceramic Capacitor 4 pF 50 V C0G/NP0"
    ],
    "inherit_model": true,
    "inherit_tags": true,
    "manufacturer": [
        true,
        ""
    ],
    "model": "96c366ee-a963-41a0-9cc8-54c646979695",
    "parametric": {
        "table": "capacitors",
        "tolerance": "20",
        "type": "C0G/NP0",
        "value": "4.0000e-12",
        "wvdc": "50.0"
    },
    "tags": [],
    "type": "part",
    "uuid": "9196ee7a-2b0c-4639-ab52-80e739842ca6",
    "value": [
        false,
        "4 pF"
    ]
}