{
    "MPN": [
        false,
        "C1005X5R1A155K050BC"
    ],
    "base": "58b92388-cb19-4e12-9c56-4cb3bf795304",
    "datasheet": [
        false,
        "https://product.tdk.com/info/en/documents/chara_sheet/C1005X5R1A155K050BC.pdf"
    ],
    "description": [
        false,
        "Ceramic Capacitor 1.5 \u00b5F 10 V X5R"
    ],
    "inherit_model": true,
    "inherit_tags": true,
    "manufacturer": [
        true,
        ""
    ],
    "model": "96c366ee-a963-41a0-9cc8-54c646979695",
    "parametric": {
        "table": "capacitors",
        "tolerance": "10",
        "type": "X5R",
        "value": "1.5000e-06",
        "wvdc": "10.0"
    },
    "tags": [],
    "type": "part",
    "uuid": "03d07f69-daab-4b88-b0bf-fa2f3269fa58",
    "value": [
        false,
        "1.5 \u00b5F"
    ]
}