{
    "MPN": [
        false,
        "GRM329B11H513KA01"
    ],
    "base": "e747f155-6606-4a43-b5fd-69c43dc541fd",
    "datasheet": [
        false,
        "https://www.murata.com/en-us/products/productdetail.aspx?partno=GRM329B11H513KA01%23"
    ],
    "description": [
        false,
        "MLCC General Purpose 51 nF, 50 V, B"
    ],
    "inherit_model": true,
    "inherit_tags": true,
    "manufacturer": [
        true,
        ""
    ],
    "model": "96c366ee-a963-41a0-9cc8-54c646979695",
    "orderable_MPNs": {},
    "parametric": {
        "table": "capacitors",
        "tolerance": "10",
        "type": "B",
        "value": "5.1000e-08",
        "wvdc": "50"
    },
    "tags": [],
    "type": "part",
    "uuid": "b18d7528-a47b-4f0a-a56a-bebb2b21dce0",
    "value": [
        false,
        "51 nF"
    ]
}