{
    "MPN": [
        false,
        "RMCF0603F_301R"
    ],
    "base": "cf9b4417-2f9c-4715-b265-0b850e19b82b",
    "datasheet": [
        true,
        ""
    ],
    "description": [
        false,
        "SMD Resistor 0603, 301 ohm, 1%, 0.1W (RMCF)"
    ],
    "inherit_model": true,
    "inherit_tags": true,
    "manufacturer": [
        true,
        ""
    ],
    "model": "96c366ee-a963-41a0-9cc8-54c646979695",
    "orderable_MPNs": {
        "be0bc474-6af0-47f2-94f3-23f081bc71b3": "RMCF0603FT301R",
        "d78867a9-3418-4727-8f5a-c8ac1efa5fae": "RMCF0603FG301R",
        "f1dece90-36c9-44f2-8760-2e6aed067bcd": "RMCF0603FB301R"
    },
    "parametric": {
        "pmax": "0.1",
        "table": "resistors",
        "tolerance": "1.0",
        "value": "301.0"
    },
    "tags": [],
    "type": "part",
    "uuid": "2919d796-754d-4e04-b7ae-036b56e6b10e",
    "value": [
        false,
        "301 \u2126"
    ]
}