{
    "MPN": [
        false,
        "RMCF0603F_3M92"
    ],
    "base": "cf9b4417-2f9c-4715-b265-0b850e19b82b",
    "datasheet": [
        true,
        ""
    ],
    "description": [
        false,
        "SMD Resistor 0603, 3.92 Mohm, 1%, 0.1W (RMCF)"
    ],
    "inherit_model": true,
    "inherit_tags": true,
    "manufacturer": [
        true,
        ""
    ],
    "model": "96c366ee-a963-41a0-9cc8-54c646979695",
    "orderable_MPNs": {
        "3ca08cd8-4e7a-40ca-a528-bc928d0641f8": "RMCF0603FT3M92",
        "5277a658-550b-4ae7-85e3-fa170c7d2fcc": "RMCF0603FB3M92",
        "663293ab-6719-414e-ad3a-417b0c58930f": "RMCF0603FG3M92"
    },
    "parametric": {
        "pmax": "0.1",
        "table": "resistors",
        "tolerance": "1.0",
        "value": "3920000.0"
    },
    "tags": [],
    "type": "part",
    "uuid": "621a63bc-8541-466b-8e92-2bf27fa846e6",
    "value": [
        false,
        "3.92 M\u2126"
    ]
}