{
    "MPN": [
        false,
        "RMCF0603J_820R"
    ],
    "base": "cf9b4417-2f9c-4715-b265-0b850e19b82b",
    "datasheet": [
        true,
        ""
    ],
    "description": [
        false,
        "SMD Resistor 0603, 820 ohm, 5%, 0.1W (RMCF)"
    ],
    "inherit_model": true,
    "inherit_tags": true,
    "manufacturer": [
        true,
        ""
    ],
    "model": "96c366ee-a963-41a0-9cc8-54c646979695",
    "orderable_MPNs": {
        "26ec0d7b-1b40-4e12-999a-0c91d1134f7c": "RMCF0603JT820R",
        "c51f7932-e7a9-47a1-ad8a-efa2e3f56021": "RMCF0603JG820R",
        "d34773f2-7a5c-4de8-b663-2fe16b2010b4": "RMCF0603JB820R"
    },
    "parametric": {
        "pmax": "0.1",
        "table": "resistors",
        "tolerance": "5.0",
        "value": "820.0"
    },
    "tags": [],
    "type": "part",
    "uuid": "a9a80b4a-fe75-4545-a11a-950cb931176c",
    "value": [
        false,
        "820 \u2126"
    ]
}