{
    "MPN": [
        false,
        "RMCF0603F_5K11"
    ],
    "base": "cf9b4417-2f9c-4715-b265-0b850e19b82b",
    "datasheet": [
        true,
        ""
    ],
    "description": [
        false,
        "SMD Resistor 0603, 5.11 Kohm, 1%, 0.1W (RMCF)"
    ],
    "inherit_model": true,
    "inherit_tags": true,
    "manufacturer": [
        true,
        ""
    ],
    "model": "96c366ee-a963-41a0-9cc8-54c646979695",
    "orderable_MPNs": {
        "5ceab7d3-2ee6-4bd7-a506-9d4226b60a3e": "RMCF0603FB5K11",
        "cb987b01-a0a3-482a-bf11-ab59069df6cb": "RMCF0603FT5K11",
        "ef3d1935-c416-4848-b30b-2906f556bd7d": "RMCF0603FG5K11"
    },
    "parametric": {
        "pmax": "0.1",
        "table": "resistors",
        "tolerance": "1.0",
        "value": "5110.0"
    },
    "tags": [],
    "type": "part",
    "uuid": "c0da5c19-a86b-4b83-81ed-678832137fb4",
    "value": [
        false,
        "5.11 k\u2126"
    ]
}