{
    "MPN": [
        false,
        "RMCF0603F_5M10"
    ],
    "base": "cf9b4417-2f9c-4715-b265-0b850e19b82b",
    "datasheet": [
        true,
        ""
    ],
    "description": [
        false,
        "SMD Resistor 0603, 5.1 Mohm, 1%, 0.1W (RMCF)"
    ],
    "inherit_model": true,
    "inherit_tags": true,
    "manufacturer": [
        true,
        ""
    ],
    "model": "96c366ee-a963-41a0-9cc8-54c646979695",
    "orderable_MPNs": {
        "1a13ced2-c6e4-4bbd-88ba-740fe66113c2": "RMCF0603FB5M10",
        "6e2c082a-0714-4748-ae79-17b7e65d96ba": "RMCF0603FT5M10",
        "955469b3-fb60-4c77-91de-8af220dda854": "RMCF0603FG5M10"
    },
    "parametric": {
        "pmax": "0.1",
        "table": "resistors",
        "tolerance": "1.0",
        "value": "5100000.0"
    },
    "tags": [],
    "type": "part",
    "uuid": "4b490f48-04ab-4d26-a2ab-9acd1a90a249",
    "value": [
        false,
        "5.1 M\u2126"
    ]
}