{
    "MPN": [
        false,
        "RMCF0603J_16K0"
    ],
    "base": "cf9b4417-2f9c-4715-b265-0b850e19b82b",
    "datasheet": [
        true,
        ""
    ],
    "description": [
        false,
        "SMD Resistor 0603, 16 Kohm, 5%, 0.1W (RMCF)"
    ],
    "inherit_model": true,
    "inherit_tags": true,
    "manufacturer": [
        true,
        ""
    ],
    "model": "96c366ee-a963-41a0-9cc8-54c646979695",
    "orderable_MPNs": {
        "39222571-a361-4cf4-a6fa-f112720216d7": "RMCF0603JG16K0",
        "53af8c38-ef2d-41b3-9f6d-1baa767b68ba": "RMCF0603JT16K0",
        "b6b6f7f0-f64b-4179-a5e6-1853c840432d": "RMCF0603JB16K0"
    },
    "parametric": {
        "pmax": "0.1",
        "table": "resistors",
        "tolerance": "5.0",
        "value": "16000.0"
    },
    "tags": [],
    "type": "part",
    "uuid": "05cd1702-a8ce-494c-bd63-41150ffb0ca2",
    "value": [
        false,
        "16 k\u2126"
    ]
}