{
    "MPN": [
        false,
        "LTC2991IMS#PBF"
    ],
    "base": "09134183-47d8-4679-9437-665e361f05dc",
    "datasheet": [
        true,
        "https://www.analog.com/media/en/technical-documentation/data-sheets/2991ff.pdf"
    ],
    "description": [
        false,
        "Octal I2C Voltage, Current & Temp Monitor (industrial; lead-free)"
    ],
    "inherit_model": true,
    "inherit_tags": true,
    "manufacturer": [
        true,
        "Analog Devices"
    ],
    "model": "3248dc34-e1d8-466a-9095-c1d079244459",
    "orderable_MPNs": {
        "d6194894-2fed-4d04-baac-477739408166": "LTC2991IMS#TRPBF"
    },
    "parametric": {},
    "tags": [],
    "type": "part",
    "uuid": "ed04262f-b73d-41af-9d4c-1f6191c596ee",
    "value": [
        true,
        "LTC2991"
    ]
}