{
    "MPN": [
        false,
        "GRM21A5C2E470JW01"
    ],
    "base": "c0222a63-8e28-4dd1-a571-04aa8736bdc9",
    "datasheet": [
        true,
        ""
    ],
    "description": [
        false,
        "Ceramic Capacitor 47 pF 250 VDC C0G/NP0"
    ],
    "inherit_model": true,
    "inherit_tags": true,
    "manufacturer": [
        true,
        ""
    ],
    "orderable_MPNs": {
        "5dd79e4f-e7a7-4295-a4da-7f310cf5cf7a": "GRM21A5C2E470JW01D",
        "6f06b29b-088e-4cdb-b82c-e680ad17445f": "GRM21A5C2E470JW01J"
    },
    "parametric": {
        "table": "capacitors",
        "type": "C0G/NP0",
        "value": "4.7000e-11",
        "wvdc": "250.0"
    },
    "tags": [],
    "type": "part",
    "uuid": "9079612e-a9b5-440a-90b1-65106537e081",
    "value": [
        false,
        "47 pF"
    ]
}