{
    "MPN": [
        false,
        "ERJ-3EKF2613"
    ],
    "base": "25f985ce-3357-4a0f-b19d-4866ef892436",
    "datasheet": [
        false,
        "https://industrial.panasonic.com/cdbs/www-data/pdf/RDA0000/AOA0000C304.pdf"
    ],
    "description": [
        false,
        "Chip Resistor 261 k\u2126 1% 0.1W"
    ],
    "inherit_model": true,
    "inherit_tags": true,
    "manufacturer": [
        true,
        ""
    ],
    "model": "96c366ee-a963-41a0-9cc8-54c646979695",
    "orderable_MPNs": {
        "710e5408-1452-4da2-94f6-d3dc9c990c6f": "ERJ-3EKF2613V"
    },
    "parametric": {
        "pmax": "0.1",
        "table": "resistors",
        "tolerance": "1.0",
        "value": "261000.0"
    },
    "tags": [],
    "type": "part",
    "uuid": "4aacbda4-e02c-4c91-bec7-b6b6c931805b",
    "value": [
        false,
        "261 k\u2126"
    ]
}