{
    "MPN": [
        false,
        "ERJ-3RBD3162"
    ],
    "base": "25f985ce-3357-4a0f-b19d-4866ef892436",
    "datasheet": [
        false,
        "https://industrial.panasonic.com/cdbs/www-data/pdf/RDA0000/AOA0000C304.pdf"
    ],
    "description": [
        false,
        "Chip Resistor 31.6 k\u2126 0% 0.1W"
    ],
    "inherit_model": true,
    "inherit_tags": true,
    "manufacturer": [
        true,
        ""
    ],
    "model": "96c366ee-a963-41a0-9cc8-54c646979695",
    "orderable_MPNs": {
        "c8751bdd-cdde-4761-99f1-cacaa761e34d": "ERJ-3RBD3162V"
    },
    "parametric": {
        "pmax": "0.1",
        "table": "resistors",
        "tolerance": "0.5",
        "value": "31600.0"
    },
    "tags": [],
    "type": "part",
    "uuid": "a8df51d7-caf9-4a37-a52b-bd968db43e3f",
    "value": [
        false,
        "31.6 k\u2126"
    ]
}