{
    "MPN": [
        false,
        "ERJ-3GEYJ274"
    ],
    "base": "25f985ce-3357-4a0f-b19d-4866ef892436",
    "datasheet": [
        false,
        "https://industrial.panasonic.com/cdbs/www-data/pdf/RDA0000/AOA0000C301.pdf"
    ],
    "description": [
        false,
        "Chip Resistor 270 k\u2126 5% 0.1W"
    ],
    "inherit_model": true,
    "inherit_tags": true,
    "manufacturer": [
        true,
        ""
    ],
    "model": "96c366ee-a963-41a0-9cc8-54c646979695",
    "orderable_MPNs": {
        "c13f607f-ca49-47d9-867b-68636722e389": "ERJ-3GEYJ274V"
    },
    "parametric": {
        "pmax": "0.1",
        "table": "resistors",
        "tolerance": "5.0",
        "value": "270000.0"
    },
    "tags": [],
    "type": "part",
    "uuid": "5c47c9ae-ded5-41b7-a496-bee5ee6708ce",
    "value": [
        false,
        "270 k\u2126"
    ]
}