{
    "MPN": [
        false,
        "ERJ-3GEYJ183"
    ],
    "base": "25f985ce-3357-4a0f-b19d-4866ef892436",
    "datasheet": [
        false,
        "https://industrial.panasonic.com/cdbs/www-data/pdf/RDA0000/AOA0000C301.pdf"
    ],
    "description": [
        false,
        "Chip Resistor 18 k\u2126 5% 0.1W"
    ],
    "inherit_model": true,
    "inherit_tags": true,
    "manufacturer": [
        true,
        ""
    ],
    "model": "96c366ee-a963-41a0-9cc8-54c646979695",
    "orderable_MPNs": {
        "f5b4c5df-4c12-4661-ab4f-1c93fa253879": "ERJ-3GEYJ183V"
    },
    "parametric": {
        "pmax": "0.1",
        "table": "resistors",
        "tolerance": "5.0",
        "value": "18000.0"
    },
    "tags": [],
    "type": "part",
    "uuid": "09284174-cc36-4ff8-9db8-10499b741842",
    "value": [
        false,
        "18 k\u2126"
    ]
}