{
    "MPN": [
        false,
        "CC0805J_X7R7BB124"
    ],
    "base": "35791498-ef97-4a72-9d63-d4468b213ec2",
    "datasheet": [
        false,
        "http://www.yageo.com/portal/product/productDocs.jsp?YageoPartNumber=CC0805JPX7R7BB124"
    ],
    "description": [
        false,
        "Ceramic Capacitor 120 nF 16 V X7R"
    ],
    "inherit_model": true,
    "inherit_tags": true,
    "manufacturer": [
        true,
        ""
    ],
    "model": "96c366ee-a963-41a0-9cc8-54c646979695",
    "orderable_MPNs": {
        "70b9b1dd-14e3-480e-a690-06a70b18373a": "CC0805JPX7R7BB124",
        "9777c95e-af94-477e-9a4f-1acbd6ef35b6": "CC0805JRX7R7BB124"
    },
    "parametric": {
        "table": "capacitors",
        "tolerance": "5",
        "type": "X7R",
        "value": "1.2000e-07",
        "wvdc": "16.0"
    },
    "tags": [],
    "type": "part",
    "uuid": "ffb8d5bb-d569-403a-8ba7-83cc6441ae6c",
    "value": [
        false,
        "120 nF"
    ]
}