{
    "MPN": [
        false,
        "CC0805C_NPO9BN3R0"
    ],
    "base": "35791498-ef97-4a72-9d63-d4468b213ec2",
    "datasheet": [
        false,
        "http://www.yageo.com/portal/product/productDocs.jsp?YageoPartNumber=CC0805CPNPO9BN3R0"
    ],
    "description": [
        false,
        "Ceramic Capacitor 3 pF 50 V NP0"
    ],
    "inherit_model": true,
    "inherit_tags": true,
    "manufacturer": [
        true,
        ""
    ],
    "model": "96c366ee-a963-41a0-9cc8-54c646979695",
    "orderable_MPNs": {
        "13f9a77b-fb3b-482a-9eb9-9b003dacb983": "CC0805CPNPO9BN3R0",
        "4ae40f67-ba6a-4424-83ae-4117e595e07f": "CC0805CRNPO9BN3R0"
    },
    "parametric": {
        "table": "capacitors",
        "tolerance": "20",
        "type": "C0G/NP0",
        "value": "3.0000e-12",
        "wvdc": "50.0"
    },
    "tags": [],
    "type": "part",
    "uuid": "1755d458-5b2e-4324-8314-3b041f76fa87",
    "value": [
        false,
        "3 pF"
    ]
}